{
  "category": "moulik_iman",
  "displayName": "মৌলিক ঈমান",
  "description": "ঈমানের স্তম্ভ ও মৌলিক বিশ্বাস",
  "questions": [
    {
      "id": 1,
      "question": "ঈমানের মূল স্তম্ভ কয়টি?",
      "options": [
        "৬টি",
        "৫টি",
        "৭টি",
        "৪টি"
      ],
      "correctAnswer": 0,
      "explanation": "ঈমানের মূল স্তম্ভ ৬টি: আল্লাহর প্রতি ঈমান, ফেরেশতাদের প্রতি ঈমান, আসমানী কিতাবসমূহের প্রতি ঈমান, নবী-রাসূলদের প্রতি ঈমান, আখিরাতের প্রতি ঈমান এবং তাকদীরের প্রতি ঈমান।",
      "difficulty": "সহজ"
    },
    {
      "id": 2,
      "question": "ইসলামের প্রথম স্তম্ভ কোনটি?",
      "options": [
        "কালিমা শাহাদাত",
        "নামাজ",
        "রোজা",
        "হজ্জ"
      ],
      "correctAnswer": 0,
      "explanation": "ইসলামের প্রথম ও সবচেয়ে গুরুত্বপূর্ণ স্তম্ভ হলো কালিমা শাহাদাত বা সাক্ষ্য প্রদান যে, আল্লাহ ছাড়া কোনো ইলাহ নেই এবং মুহাম্মদ (ﷺ) আল্লাহর রাসূল।",
      "difficulty": "সহজ"
    },
    {
      "id": 3,
      "question": "ইসলামের মূল স্তম্ভ কয়টি?",
      "options": [
        "৫টি",
        "৬টি",
        "৭টি",
        "৪টি"
      ],
      "correctAnswer": 0,
      "explanation": "ইসলামের মূল স্তম্ভ ৫টি: কালিমা, নামাজ, রোজা, যাকাত এবং হজ্জ।",
      "difficulty": "সহজ"
    },
    {
      "id": 4,
      "question": "আল্লাহর কতটি সুন্দর নাম রয়েছে?",
      "options": [
        "৯৯টি",
        "১০০টি",
        "৯৫টি",
        "৮৫টি"
      ],
      "correctAnswer": 0,
      "explanation": "হাদীসে বর্ণিত আছে যে, আল্লাহর ৯৯টি সুন্দর নাম (আসমাউল হুসনা) রয়েছে।",
      "difficulty": "সহজ"
    },
    {
      "id": 5,
      "question": "কোন ফেরেশতা ওহী নিয়ে আসতেন?",
      "options": [
        "জিবরাঈল (আ.)",
        "মিকাঈল (আ.)",
        "ইসরাফিল (আ.)",
        "আজরাঈল (আ.)"
      ],
      "correctAnswer": 0,
      "explanation": "হযরত জিবরাঈল (আ.) ছিলেন ওহী বহনকারী ফেরেশতা যিনি আল্লাহর বাণী নবী-রাসূলদের কাছে পৌঁছে দিতেন।",
      "difficulty": "সহজ"
    },
    {
      "id": 6,
      "question": "কোন ফেরেশতা কিয়ামতের দিন শিঙ্গায় ফুঁক দেবেন?",
      "options": [
        "ইসরাফিল (আ.)",
        "জিবরাঈল (আ.)",
        "মিকাঈল (আ.)",
        "আজরাঈল (আ.)"
      ],
      "correctAnswer": 0,
      "explanation": "হযরত ইসরাফিল (আ.) কিয়ামতের দিন শিঙ্গায় ফুঁক দেওয়ার দায়িত্বে নিয়োজিত ফেরেশতা।",
      "difficulty": "সহজ"
    },
    {
      "id": 7,
      "question": "কোন ফেরেশতা মৃত্যুর দায়িত্বে নিয়োজিত?",
      "options": [
        "আজরাঈল (আ.)",
        "ইসরাফিল (আ.)",
        "মিকাঈল (আ.)",
        "জিবরাঈল (আ.)"
      ],
      "correctAnswer": 0,
      "explanation": "হযরত আজরাঈল (আ.) মালাকুল মাউত বা মৃত্যুর ফেরেশতা যিনি প্রাণ হরণের দায়িত্বে নিয়োজিত।",
      "difficulty": "সহজ"
    },
    {
      "id": 8,
      "question": "প্রথম নবী কে ছিলেন?",
      "options": [
        "হযরত আদম (আ.)",
        "হযরত নূহ (আ.)",
        "হযরত ইবরাহীম (আ.)",
        "হযরত মূসা (আ.)"
      ],
      "correctAnswer": 0,
      "explanation": "হযরত আদম (আ.) ছিলেন প্রথম মানুষ এবং প্রথম নবী।",
      "difficulty": "সহজ"
    },
    {
      "id": 9,
      "question": "সর্বশেষ নবী কে?",
      "options": [
        "হযরত মুহাম্মদ (ﷺ)",
        "হযরত ঈসা (আ.)",
        "হযরত মূসা (আ.)",
        "হযরত ইবরাহীম (আ.)"
      ],
      "correctAnswer": 0,
      "explanation": "হযরত মুহাম্মদ (ﷺ) হলেন সর্বশেষ নবী ও রাসূল। তাঁর পরে আর কোনো নবী আসবেন না।",
      "difficulty": "সহজ"
    },
    {
      "id": 10,
      "question": "চারটি প্রধান আসমানী কিতাব কোনগুলো?",
      "options": [
        "তাওরাত, যাবুর, ইঞ্জিল ও কুরআন",
        "তাওরাত, সহীফা, ইঞ্জিল ও কুরআন",
        "যাবুর, সহীফা, ইঞ্জিল ও কুরআন",
        "তাওরাত, যাবুর, সহীফা ও কুরআন"
      ],
      "correctAnswer": 0,
      "explanation": "চারটি প্রধান আসমানী কিতাব হলো: তাওরাত (মূসা আ.), যাবুর (দাউদ আ.), ইঞ্জিল (ঈসা আ.) এবং কুরআন (মুহাম্মদ ﷺ)।",
      "difficulty": "সহজ"
    }
  ]
}