{
    "title": "নামাজের নিয়মাবলী",
    "content": [
        {
            "heading": "১. সালাতের গুরুত্ব",
            "body": "সালাত মুমিনের জন্য শ্রেষ্ঠ ইবাদত। আল্লাহ বলেন: 'নিশ্চয়ই সালাত মানুষকে মন্দ কাজ থেকে বিরত রাখে।' (সূরা আনকাবুত: ৪৫)। কেয়ামতের দিন সর্বপ্রথম নামাজের হিসাব নেওয়া হবে।"
        },
        {
            "heading": "২. নামাজের ফরজ কাজ",
            "body": "নামাজের বাইরে ৭টি এবং ভেতরে ৬টি কাজ ফরজ।\n\nবাইরের কাজ: শরীর, কাপড় ও জায়গা পবিত্র হওয়া, সতর ঢাকা, কিবলামুখী হওয়া, ওয়াক্ত হওয়া এবং নিয়ত করা।\n\nভেতরের কাজ: তাকবীর বলা, দাঁড়িয়ে পড়া, কিরাত পাঠ করা, রুকু করা, সিজদাহ করা এবং শেষ বৈঠকে বসা।"
        },
        {
            "heading": "৩. সালাত আদায়ের নিয়ম ও সর্তকতা",
            "body": "মনোযোগের সাথে কিবলামুখী হয়ে সালাত আদায় করতে হয়। প্রতিটি অঙ্গ সুন্নাত অনুযায়ী ধীরস্থিরভাবে আদায় করা আবশ্যক। নামাজের মাঝে কথা বললে, কিছু পানাহার করলে বা উচ্চস্বরে হাসলে নামাজ ভেঙ্গে যায়।"
        }
    ]
}