{"category_id":"fiqh_taharat","category_name":"তাহারাত ও পবিত্রতা","total_questions":200,"questions":[{"id":1,"question":"ইসলামী শরীয়ত অনুযায়ী ইবাদত কবুল হওয়ার জন্য প্রথম শর্ত কোনটি?","options":["নতুন পোশাক","তাহারাত বা পবিত্রতা","সুগন্ধি মাখা","বেশি টাকা"],"correct_answer":1,"explanation":"পবিত্রতা ঈমানের অর্ধেক এবং সালাত কবুল হওয়ার পূর্বশর্ত।"},{"id":2,"question":"অযু করার সময় কয়টি কাজ করা ফরজ বা বাধ্যতামূলক?","options":["৩টি","৪টি","৬টি","১০টি"],"correct_answer":1,"explanation":"১. মুখ ধোয়া ২. দুই হাত কনুইসহ ধোয়া ৩. মাথা মাসাহ ৪. দুই পা টাখনুসহ ধোয়া।"},{"id":"3","question":"অযুর শুরুতে ‘বিসমিল্লাহ’ পাঠ করা শরীয়তের দৃষ্টিতে কেমন কাজ?","text":"অযুর শুরুতে ‘বিসমিল্লাহ’ পাঠ করা শরীয়তের দৃষ্টিতে কেমন কাজ?","options":["ফরজ","ওয়াজিব","সুন্নত","মুস্তাহাব"],"correctAnswer":2,"correct_answer":2,"correctIndex":2,"explanation":"সব ভালো কাজের শুরুতে বিসমিল্লাহ বলা নবীজির সুন্নাত। অযুর শুরুতে বিসমিল্লাহ পড়া সুন্নত মুয়াক্কাদাহ, অর্থাৎ একটি প্রতিষ্ঠিত সুন্নত।"},{"id":4,"question":"অযুর সময় পূর্ণ মাথা কতবার মাসাহ করা সুন্নাত?","options":["১ বার","৩ বার","৫ বার","১০ বার"],"correct_answer":0,"explanation":"মাথা মাসাহ একবার করা সুন্নাত, তবে ধোয়া অঙ্গগুলো তিনবার ধোয়া সুন্নাত।"},{"id":5,"question":"কোন ধরণের পানি দিয়ে অযু বা গোসল করা জায়েজ নয়?","options":["বৃষ্টির পানি","ব্যবহৃত বা নাপাক মিশ্রিত পানি","সমুদ্রের পানি","কূপের পানি"],"correct_answer":1,"explanation":"পবিত্রতা অর্জনের জন্য পানিকে অবশ্যই পরিষ্কার ও নাপাকি মুক্ত হতে হবে।"},{"id":6,"question":"গোসলের ফরজ কাজ কয়টি?","options":["১টি","৩টি","৫টি","৭টি"],"correct_answer":1,"explanation":"১. কুলি করা ২. নাকে পানি দেওয়া ৩. সারা শরীরে পানি পৌঁছানো।"},{"id":7,"question":"পানি না পাওয়া গেলে পবিত্র মাটি দিয়ে পবিত্রতা অর্জন করাকে কী বলে?","options":["অযু","তায়াম্মুম","মাসাহ","ইস্তিনজা"],"correct_answer":1,"explanation":"বিশেষ পরিস্থিতিতে পানির বিকল্প হিসেবে তায়াম্মুমের বিধান দেওয়া হয়েছে।"},{"id":8,"question":"তায়াম্মুমের ফরজ কাজ কয়টি?","options":["২টি","৩টি (নিয়ত, মুখ ও হাত মাসাহ)","৪টি","৫টি"],"correct_answer":1,"explanation":"পবিত্র মাটির ওপর হাত মেরে মুখ ও দুই হাত মাসাহ করা ফরজ।"},{"id":9,"question":"অযু অবস্থায় ঘুমিয়ে পড়লে অযুর কী অবস্থা হয়?","options":["অযু থাকে","অযু ভেঙে যায়","সওয়াব বাড়ে","মকরুহ হয়"],"correct_answer":1,"explanation":"গভীর ঘুম যা নিয়ন্ত্রণ হারায়, তা অযু ভঙ্গের অন্যতম কারণ।"},{"id":10,"question":"শরীরের কোনো ক্ষতস্থান থেকে রক্ত বা পুঁজ গড়িয়ে পড়লে অযুর বিধান কী?","options":["অযু থাকে","অযু ভেঙে যায় (হানাফী মতে)","সহীহ থাকে","কাফফারা লাগে"],"correct_answer":1,"explanation":"প্রবাহিত রক্ত বা নাপাকি অযু নষ্ট করে দেয়।"},{"id":11,"question":"অযুর সময় মেসওয়াক করা শরীয়তের দৃষ্টিতে কেমন কাজ?","options":["ফরজ","সুন্নত","ওয়াজিব","মুবাহ"],"correct_answer":1,"explanation":"মেসওয়াক করা আল্লাহর সন্তুষ্টি ও মুখের পবিত্রতার মাধ্যম।"},{"id":12,"question":"পেশাব বা পায়খানার পর পবিত্র হওয়াকে ফিকহী ভাষায় কী বলে?","options":["সালাত","ইস্তিনজা","জিকির","ওমরাহ"],"correct_answer":1,"explanation":"পানি বা ঢিলা ব্যবহার করে নাপাকি দূর করাই ইস্তিনজা।"},{"id":13,"question":"পুরুষদের জন্য গোসলের সময় দাড়ি বা চুলের গোড়ায় পানি পৌঁছানো কী?","options":["নফল","ফরজ","সুন্নত","ঐচ্ছিক"],"correct_answer":1,"explanation":"শরীরের প্রতিটি পশমের গোড়ায় পানি পৌঁছানো গোসলের আবশ্যিক শর্ত।"},{"id":14,"question":"তায়াম্মুম করার জন্য কোন ধরণের মাটি ব্যবহার করা জরুরি?","options":["কাদা মাটি","পবিত্র ধূলিযুক্ত মাটি বা পাথর","বালুহীন মাটি","ভেজা মাটি"],"correct_answer":1,"explanation":"পবিত্র ও শুষ্ক মাটি তায়াম্মুমের জন্য উপযুক্ত।"},{"id":15,"question":"মোজার ওপর মাসাহ করার সময়সীমা মুসাফিরের জন্য কতদিন?","options":["১ দিন ১ রাত","৩ দিন ৩ রাত","৭ দিন","১০ দিন"],"correct_answer":1,"explanation":"চামড়ার মোজা পরে মুসাফির তিন দিন পর্যন্ত মাসাহ করতে পারেন।"},{"id":16,"question":"মোজার ওপর মাসাহ করার সময়সীমা মুকিম বা সাধারণ ব্যক্তির জন্য কতটুকু?","options":["১ দিন ১ রাত","২ দিন","৩ দিন","৫ দিন"],"correct_answer":0,"explanation":"বাড়িতে অবস্থানকালে ২৪ ঘণ্টা পর্যন্ত মোজার ওপর মাসাহ করা জায়েজ।"},{"id":17,"question":"অযু করার পর শরীরে তেল মাখলে অযুর কী হয়?","options":["ভেঙে যায়","অযু নষ্ট হয় না","মকরুহ হয়","হারাম হয়"],"correct_answer":1,"explanation":"তেল মাখা অযু ভঙ্গের কোনো কারণ নয়।"},{"id":18,"question":"অযু অবস্থায় শরীর থেকে নখ বা চুল কাটলে অযুর কী পরিবর্তন হয়?","options":["অযু ভেঙে যায়","অযু নষ্ট হয় না","কাফফারা লাগে","মাফ চেয়ে নিতে হয়"],"correct_answer":1,"explanation":"নখ বা চুল কাটলে অযু ভাঙার কোনো দলিল নেই।"},{"id":19,"question":"কোন ধরণের নাপাকিকে 'নাজাসাতে গালিজাহ' বা ভারী নাপাকি বলা হয়?","options":["মদ, রক্ত ও বিষ্ঠা","মাটির কণা","ঘাম","সর্দি"],"correct_answer":0,"explanation":"এই নাপাকিগুলো কাপড়ে লাগলে ধোয়া বাধ্যতামূলক।"},{"id":20,"question":"অযুর শেষে আকাশ পানে তাকিয়ে কোন দোয়া পড়া সুন্নাত?","options":["সুরা ইখলাস","কালিমা শাহাদাত","দোয়া মাসুরা","দোয়া কুনুত"],"correct_answer":1,"explanation":"কালিমা শাহাদাত পাঠকারীর জন্য জান্নাতের ৮টি দরজা খুলে দেওয়া হয়।"},{"id":21,"question":"তায়াম্মুম করা অবস্থায় পানি পাওয়া গেলে তায়াম্মুমের কী হয়?","options":["সহীহ থাকে","তায়াম্মুম ভেঙে যায়","সওয়াব বাড়ে","কিছু হয় না"],"correct_answer":1,"explanation":"পানির উপস্থিতি তায়াম্মুমের বৈধতা শেষ করে দেয়।"},{"id":22,"question":"গোসলের সময় কানে বা নাকে পানি না পৌঁছালে গোসলের অবস্থা কী হবে?","options":["সহীহ হবে","গোসল অসম্পূর্ণ বা হবে না","মকরুহ হবে","সুন্নত হবে"],"correct_answer":1,"explanation":"শরীরের প্রতিটি ছিদ্রপথে পানি পৌঁছানো ফরজ।"},{"id":23,"question":"ব্যবহৃত পোশাক পবিত্র করার জন্য কমপক্ষে কতবার ধোয়া উত্তম?","options":["১ বার","৩ বার","১০ বার","১০০ বার"],"correct_answer":1,"explanation":"নাপাকি দূর না হওয়া পর্যন্ত ধোয়া এবং তিনবার ধোয়া সুন্নাত।"},{"id":24,"question":"কোন পশু পানি পান করলে ওই পানি নাপাক হয়ে যায়?","options":["বিড়াল","কুকুর ও শূকর","পাখি","গরু"],"correct_answer":1,"explanation":"কুকুরের লালা নাপাক বিধায় ওই পানি ব্যবহার করা যায় না।"},{"id":25,"question":"ইস্তিনজা করার সময় কোন হাত ব্যবহার করা সুন্নাত বা আদব?","options":["ডান হাত","বাম হাত","উভয় হাত","পায়ের আঙ্গুল"],"correct_answer":1,"explanation":"পবিত্রতা অর্জনের কাজে বাম হাত ব্যবহার করা নবীজির শিক্ষা।"},{"id":26,"question":"অযুর সময় ঘাড় মাসাহ করা ফিকহী দৃষ্টিতে কেমন কাজ?","options":["ফরজ","মুস্তাহাব বা আদব","মকরুহ","হারাম"],"correct_answer":1,"explanation":"মাথা মাসাহর সাথে ঘাড়ের পেছনের অংশ মাসাহ করা ভালো।"},{"id":27,"question":"গোসলের সময় কুলকুচা বা কুলি করা কোন পর্যায়ের বিধান?","options":["নফল","ফরজ","সুন্নত","মুবাহ"],"correct_answer":1,"explanation":"মুখের ভেতর পরিষ্কার করা গোসলের প্রধান তিন ফরজের একটি।"},{"id":28,"question":"তায়াম্মুমের সময় দুই হাত কতটুকু মাসাহ করা ফরজ?","options":["কব্জি পর্যন্ত","কনুই পর্যন্ত","কাঁধ পর্যন্ত","আঙ্গুল পর্যন্ত"],"correct_answer":1,"explanation":"মাটির তালু দিয়ে দুই হাত কনুইসহ একবার মুছা ফরজ।"},{"id":29,"question":"নামাযের ভেতর শব্দ করে হাসলে অযুর কী হয় (হানাফী মতে)?","options":["অযু থাকে","অযু ভেঙে যায়","কিছু হয় না","পাপ হয়"],"correct_answer":1,"explanation":"এটি সালাতের গাম্ভীর্য নষ্ট করে বলে অযুকেও নষ্ট করে দেয়।"},{"id":30,"question":"কুকুরের লালা লাগা পাত্র পবিত্র করার জন্য কয়বার ধোয়ার নির্দেশ আছে?","options":["১ বার","৭ বার (একবার মাটি দিয়ে)","৩ বার","১০ বার"],"correct_answer":1,"explanation":"কুকুরের নাপাকি দূর করার জন্য সাতবার ধোয়া সুন্নাত।"},{"id":31,"question":"অযুর সময় দাড়ি খিলাল করা শরীয়তের দৃষ্টিতে কেমন?","options":["ফরজ","সুন্নত","ওয়াজিব","নফল"],"correct_answer":1,"explanation":"দাড়ির ফাঁকে আঙ্গুল দিয়ে পানি পৌঁছানো নবীজির আমল।"},{"id":32,"question":"গোসলের সময় নাকে পানি দেওয়া কোন পর্যায়ের কাজ?","options":["সুন্নত","ফরজ","নফল","মকরুহ"],"correct_answer":1,"explanation":"নাকের নরম হাড় পর্যন্ত পানি পৌঁছানো গোসলের ফরজ।"},{"id":33,"question":"অযু করার পর উলঙ্গ হলে কি অযু ভেঙে যায়?","options":["হ্যাঁ","না, অযু সহীহ থাকে","মকরুহ হয়","জানিনা"],"correct_answer":1,"explanation":"পোশাক পরিবর্তন বা উলঙ্গ হওয়া অযু ভঙ্গের কারণ নয়।"},{"id":34,"question":"তায়াম্মুম করার সময় হাতের আঙ্গুল খিলাল করা কেমন?","options":["ফরজ","সুন্নত","মকরুহ","ওয়াজিব"],"correct_answer":1,"explanation":"আঙ্গুলের ফাঁকগুলো মাসাহ করা সুন্নাত।"},{"id":35,"question":"মোজার ওপর মাসাহ করার জন্য মোজাটি কেমন হওয়া শর্ত?","options":["সুতি","চামড়ার বা বিশেষ পুরুত্বের","পাতলা","ছেঁড়া"],"correct_answer":1,"explanation":"পাতলা সুতি মোজায় মাসাহ জায়েজ নয়।"},{"id":36,"question":"রক্ত ছাড়া অন্য কোনো দেহনিঃসৃত তরল (যেমন: লসিকা) বের হলে অযুর বিধান কী?","options":["ভেঙে যায়","প্রবাহিত হলে অযু ভেঙে যায়","সহীহ থাকে","কাফফারা লাগে"],"correct_answer":1,"explanation":"নাপাক কোনো কিছু প্রবাহিত হলেই অযু নষ্ট হয়।"},{"id":37,"question":"অযুর সময় কুলি করার সময় কয়বার পানি নেওয়া সুন্নাত?","options":["১ বার","৩ বার","৫ বার","১০ বার"],"correct_answer":1,"explanation":"মুখের ভেতরে তিনবার পানি নিয়ে পরিষ্কার করা সুন্নাত।"},{"id":38,"question":"গোসলের সময় চুলে বেণী করা থাকলে মহিলারা কী করবেন?","options":["বেণী খোলা ফরজ","গোড়ায় পানি পৌঁছালে বেণী খোলা জরুরি নয়","কেটে ফেলা","জানিনা"],"correct_answer":1,"explanation":"যদি চুলের গোড়া ভিজে যায় তবে বেণী না খুললেও চলে।"},{"id":39,"question":"তায়াম্মুম করার জন্য মাটির পরিবর্তে আর কী ব্যবহার করা যায়?","options":["কাঠ","ধুলাবালি যুক্ত পাথর বা দেয়াল","কাঁচ","লোহা"],"correct_answer":1,"explanation":"মাটি জাতীয় যেকোনো পবিত্র বস্তু দিয়ে তায়াম্মুম করা যায়।"},{"id":40,"question":"অযুর সময় দুই পা কতটুকু ধোয়া ফরজ?","options":["আঙ্গুল পর্যন্ত","টাখনু বা গিটসহ","হাঁটু পর্যন্ত","কোমর পর্যন্ত"],"correct_answer":1,"explanation":"পায়ের গোড়ালি ও গিটসহ ভালোভাবে ধোয়া অযুর শর্ত।"},{"id":41,"question":"ইস্তিনজার জন্য ঢিলা বা কুলুখ ব্যবহার করার পর পানি ব্যবহারের মর্যাদা কী?","options":["মকরুহ","অত্যন্ত উত্তম ও সুন্নাত","নিষিদ্ধ","ওয়াজিব নয়"],"correct_answer":1,"explanation":"উভয় পদ্ধতি একত্রে ব্যবহার করা পূর্ণ পবিত্রতার জন্য শ্রেষ্ঠ।"},{"id":42,"question":"অযুর সময় কানে আঙ্গুল দিয়ে মাসাহ করা কেমন কাজ?","options":["ফরজ","সুন্নত","নফল","মকরুহ"],"correct_answer":1,"explanation":"মাথা মাসাহর সাথে কান পরিষ্কার করা সুন্নাত।"},{"id":43,"question":"অযু করার পর বিড়ি বা সিগারেট খেলে অযুর কী হয়?","options":["ভেঙে যায়","অযু নষ্ট হয় না (তবে মুখ দুর্গন্ধযুক্ত হয়)","সওয়াব বাড়ে","হারাম হয়"],"correct_answer":1,"explanation":"এটি অযু ভঙ্গের কারণ না হলেও ইবাদতের আদবের পরিপন্থী।"},{"id":44,"question":"তায়াম্মুমের সময় তায়াম্মুমের জন্য কিসের নিয়ত করা জরুরি?","options":["স্নানের","পবিত্রতা অর্জন বা নামায বৈধ করার নিয়ত","ভ্রমণের","পানির"],"correct_answer":1,"explanation":"নিয়ত ছাড়া তায়াম্মুম সওয়াবহীন একটি কাজ।"},{"id":45,"question":"মোজার ওপর মাসাহ করার জন্য মোজাটি কখন পরতে হয়?","options":["যেকোনো সময়","পূর্ণ অযু করার পর","ঘুমানোর আগে","অসুস্থ হলে"],"correct_answer":1,"explanation":"পবিত্র অবস্থায় মোজা না পরলে মাসাহ বৈধ হবে না।"},{"id":46,"question":"শরীরের কোনো অংশে ব্যান্ডেজ থাকলে তার ওপর অযু করার নিয়ম কী?","options":["ব্যান্ডেজ খোলা ফরজ","ব্যান্ডেজের ওপর মাসাহ করা (মাসেহ আলাল জাবীরা)","অযু না করা","কাফফারা দেওয়া"],"correct_answer":1,"explanation":"ক্ষতি হওয়ার ভয় থাকলে ব্যান্ডেজের ওপর দিয়ে ভিজা হাত বুলানোই যথেষ্ট।"},{"id":47,"question":"অযুর সময় নাকে কতবার পানি দিয়ে পরিষ্কার করা সুন্নাত?","options":["১ বার","৩ বার","১০ বার","৫ বার"],"correct_answer":1,"explanation":"তিনবার আলাদা পানি নিয়ে নাক ঝাড়া সুন্নাত।"},{"id":48,"question":"গোসলের পর পুনরায় অযু করার বিধান কী?","options":["ফরজ","প্রয়োজন নেই (গোসলেই অযু হয়ে যায়)","ওয়াজিব","মকরুহ"],"correct_answer":1,"explanation":"সঠিকভাবে গোসল করলে আলাদা করে অযু করার দরকার হয় না।"},{"id":49,"question":"তায়াম্মুমের সময় মাটি কি ঘষে মুখে মাখতে হয়?","options":["হ্যাঁ","না, আলতোভাবে হাত বুলিয়ে মাসাহ করতে হয়","পাথর দিয়ে","কিছুই না"],"correct_answer":1,"explanation":"তায়াম্মুম মূলত একটি প্রতীকী পবিত্রতা অর্জন।"},{"id":50,"question":"অযুর পানির অপচয় করা শরীয়তের দৃষ্টিতে কেমন?","options":["সওয়াব","মকরুহ ও অপছন্দনীয়","জায়েজ","প্রয়োজনীয়"],"correct_answer":1,"explanation":"নদী বা সমুদ্রের পাড়ে থাকলেও অহেতুক পানি খরচ করা নিষেধ।"},{"id":51,"question":"অযু ভাঙার মোট কারণ ফিকহশাস্ত্রে কয়টি বলা হয়েছে?","options":["৫টি","৭টি (প্রধান কারণ)","১০টি","১২টি"],"correct_answer":1,"explanation":"সাধারণভাবে অযু ভঙ্গের সাতটি মূল কারণ চিহ্নিত করা হয়েছে।"},{"id":52,"question":"অযুর সময় কোন অঙ্গটি দিয়ে শুরু করা সুন্নাত?","options":["বাম অঙ্গ","ডান অঙ্গ","উভয় একসাথে","মাথা"],"correct_answer":1,"explanation":"সব ভালো কাজে ডান দিক দিয়ে শুরু করা নবীজির পদ্ধতি।"},{"id":53,"question":"কোন ওজরে তায়াম্মুম করা জায়েজ?","options":["আলস্য","এক মাইলের মধ্যে পানি না থাকলে বা রোগ বাড়ার ভয় থাকলে","ঠান্ডা লাগলে","ভ্রমণে গেলে"],"correct_answer":1,"explanation":"পানির অনুপস্থিতি বা পানি ব্যবহারে শারীরিক ক্ষতির সম্ভাবনা তায়াম্মুমের ওজর।"},{"id":54,"question":"অযুর সময় কপাল থেকে থুতনি পর্যন্ত মুখ ধোয়া কোন পর্যায়ের কাজ?","options":["সুন্নত","ফরজ","ওয়াজিব","নফল"],"correct_answer":1,"explanation":"মুখমণ্ডল ধৌত করা অযুর অন্যতম ফরজ।"},{"id":55,"question":"ঢিলা বা কুলুখ ব্যবহারের পর পানি ব্যবহার করাকে কী বলে?","options":["তাহারাত","এস্তেঞ্জা","সালাত","জিকির"],"correct_answer":1,"explanation":"এটি পূর্ণাঙ্গ পবিত্রতা অর্জনের সুন্নাত পদ্ধতি।"},{"id":56,"question":"অযুর সময় হাতের আঙ্গুলের আংটি বা চুড়ি থাকলে করণীয় কী?","options":["ফেলে দেওয়া","সেগুলোর নিচে পানি পৌঁছানো নিশ্চিত করা","কিছু না করা","নতুন কেনা"],"correct_answer":1,"explanation":"চামড়া পর্যন্ত পানি না পৌঁছালে অযু হবে না।"},{"id":57,"question":"গোসলের সময় কুলি করার সময় গড়গড়া করা কখন সুন্নাত?","options":["সব সময়","রোজা না থাকলে","ঘুমানোর আগে","খাওয়ার পর"],"correct_answer":1,"explanation":"রোজার অবস্থায় পানি পেটে যাওয়ার ভয় থাকে বলে গড়গড়া বর্জন করতে হয়।"},{"id":58,"question":"তায়াম্মুম করার সময় হাতের কব্জির ওপর ঘড়ি থাকলে কী করতে হয়?","options":["রেখে দেওয়া","ঘড়ি সরিয়ে তার নিচের অংশ মাসাহ করা","হাত না মুছা","পাথর মাখা"],"correct_answer":1,"explanation":"মাসাহর জন্য চামড়া স্পর্শ করা শর্ত।"},{"id":59,"question":"মোজার ওপর মাসাহ করার সময় হাতের কয়টি আঙ্গুল ব্যবহার করা সুন্নাত?","options":["১টি","৩টি","সবগুলো","পায়ের আঙ্গুল"],"correct_answer":1,"explanation":"হাতের ওপরের তিন আঙ্গুল দিয়ে মোজার উপরিভাগ মাসাহ করা নিয়ম।"},{"id":60,"question":"অযু করার পর শরীরে রক্ত জমার দাগ থাকলে অযুর কী হয়?","options":["ভেঙে যায়","অযু নষ্ট হয় না (রক্ত প্রবাহিত না হলে)","মকরুহ","হারাম"],"correct_answer":1,"explanation":"শুধুমাত্র প্রবাহিত নাপাকি অযু নষ্ট করে।"},{"id":61,"question":"অযুর পানির ছিটা শরীরে বা কাপড়ে লাগলে বিধান কী?","options":["কাপড় নাপাক হয়","অযুর পানি পবিত্র বলে কাপড় নাপাক হয় না","হারাম","পাপ"],"correct_answer":1,"explanation":"অযুর ব্যবহৃত পানি নাপাক নয়।"},{"id":62,"question":"অযুর সময় হাতের কনুই ধোয়া কোন পর্যায়ের বিধান?","options":["সুন্নত","ফরজ","নফল","ঐচ্ছিক"],"correct_answer":1,"explanation":"দুই হাত কনুইসহ ধৌত করা অযুর অন্যতম ফরজ।"},{"id":63,"question":"তায়াম্মুমের সময় মুখে হাত কতবার বোলাতে হয়?","options":["১ বার","৩ বার","১০ বার","৫ বার"],"correct_answer":0,"explanation":"মুখ একবার মাসাহ করাই তায়াম্মুমের ফরজ আদায়ের জন্য যথেষ্ট।"},{"id":64,"question":"ইস্তিনজা করার জন্য হাড় বা গোবর ব্যবহার করা কেমন?","options":["জায়েজ","নিষিদ্ধ বা মকরুহ তাহরীমি","সওয়াব","জানিনা"],"correct_answer":1,"explanation":"নবীজি (সা.) এগুলো দিয়ে পবিত্র হতে নিষেধ করেছেন।"},{"id":65,"question":"অযুর সময় ঘাড়ের সামনের অংশ বা গলা মাসাহ করা কী?","options":["সুন্নত","বিদাআত বা নিষিদ্ধ","ওয়াজিব","মুস্তাহাব"],"correct_answer":1,"explanation":"ঘাড় মাসাহর সময় গলা মাসাহ করা শরিয়তে নেই।"},{"id":66,"question":"গোসলের ফরজ কাজগুলো করার আগে কোনটি করা সুন্নাত?","options":["আযান দেওয়া","মিসওয়াক ও অযু করা","গান গাওয়া","বসে থাকা"],"correct_answer":1,"explanation":"গোসলের আগে অযুর সুন্নাতগুলো পালন করা সওয়াবের কাজ।"},{"id":67,"question":"তায়াম্মুমের সময় কি বিসমিল্লাহ বলা জরুরি?","options":["না","হ্যাঁ, এটি অযুর মতোই সুন্নাত","মাঝে মাঝে","ভুলে হলে হয়"],"correct_answer":1,"explanation":"ইবাদতের শুরুতে আল্লাহর নাম নেওয়া বরকতময়।"},{"id":68,"question":"মোজার ওপর মাসাহ করার সময় পায়ের তালু মাসাহ করলে কী হবে?","options":["সহীহ হবে","মাসাহ হবে না (উপরিভাগ মাসাহ করা শর্ত)","মকরুহ","সওয়াব"],"correct_answer":1,"explanation":"সুন্নাত হলো পায়ের উপরের অংশ মাসাহ করা।"},{"id":69,"question":"অযুর সময় কথা বলা শরীয়তের দৃষ্টিতে কেমন?","options":["হারাম","অনুচিত বা মকরুহ তানজিহী","সওয়াব","ফরজ"],"correct_answer":1,"explanation":"অযুর সময় জিকির বা দোয়াতে মশগুল থাকা ভালো।"},{"id":70,"question":"গোসলের সময় শরীরে কোনো জায়গাতে পানি না পৌঁছালে কী হয়?","options":["সহীহ হয়","নাপাকি দূর হয় না এবং গোসল হয় না","মকরুহ","ওয়াজিব"],"correct_answer":1,"explanation":"সম্পূর্ণ শরীর ধৌত করা গোসলের অপরিহার্য শর্ত।"},{"id":71,"question":"অযু অবস্থায় বমি করলে অযুর বিধান কী?","options":["অযু থাকে","মুখ ভর্তি বমি হলে অযু ভেঙে যায় (হানাফী মতে)","সওয়াব","জানিনা"],"correct_answer":1,"explanation":"অল্প বমিতে অযু ভাঙে না, কিন্তু বেশি হলে নষ্ট হয়।"},{"id":72,"question":"অযুর সময় মাথা মাসাহ করার ফরজের পরিমাণ কতটুকু?","options":["পুরো মাথা","মাথার চার ভাগের এক ভাগ (হানাফী মতে)","শুধু কপাল","শুধু কান"],"correct_answer":1,"explanation":"অংশবিশেষ মাসাহ করলেই ফরজ আদায় হয়ে যায়।"},{"id":73,"question":"তায়াম্মুম কি হজ্জ বা বড় কোনো ইবাদতের জন্য বৈধ?","options":["না","হ্যাঁ, যদি পানির অভাব বা ওজর থাকে","হারাম","নিষিদ্ধ"],"correct_answer":1,"explanation":"পবিত্রতা সবক্ষেত্রে তায়াম্মুমের মাধ্যমে অর্জন করা যায়।"},{"id":74,"question":"অযুর সময় পায়ের আঙ্গুল খিলাল করা কেমন কাজ?","options":["ফরজ","সুন্নত","মকরুহ","নফল"],"correct_answer":1,"explanation":"আঙ্গুলের ফাঁক পরিষ্কার রাখা নবীজির শিক্ষা।"},{"id":75,"question":"গোসলের পর কি নতুন করে অযু ছাড়াই নামায পড়া যায়?","options":["না","হ্যাঁ, যদি গোসল সঠিক পদ্ধতিতে হয়","হারাম","পাপ"],"correct_answer":1,"explanation":"গোসলের ভেতর অযু স্বয়ংক্রিয়ভাবে অন্তর্ভুক্ত থাকে।"},{"id":76,"question":"তায়াম্মুম করার জন্য মাটির রঙের কোনো শর্ত আছে কি?","options":["হ্যাঁ","না, পবিত্র মাটি হওয়া ই যথেষ্ট","লাল হতে হবে","সাদা হতে হবে"],"correct_answer":1,"explanation":"মাটির রঙ পবিত্রতায় কোনো বাধা নয়।"},{"id":77,"question":"অযুর সময় কানে পানি ঢোকানো কি জরুরি?","options":["হ্যাঁ","না, কেবল ভিজা আঙ্গুল দিয়ে মাসাহ করলেই হবে","হারাম","জানিনা"],"correct_answer":1,"explanation":"কানের পর্দা রক্ষার জন্য ভেতরে পানি না ঢুকিয়ে মাসাহ করাই সুন্নাত।"},{"id":78,"question":"অযুর শেষে কালিমা পড়ার মর্যাদা কী?","options":["টাকা পাওয়া","জান্নাতের সুসংবাদ","বিদেশে যাওয়া","রাজত্ব"],"correct_answer":1,"explanation":"দোয়াটি হলো জান্নাত লাভের এক বিশেষ চাবিকাঠি।"},{"id":79,"question":"অযু অবস্থায় হাসলে কি অযু ভেঙে যায় (নামাযের বাইরে)?","options":["হ্যাঁ","না, নামাযের বাইরে হাসলে অযু নষ্ট হয় না","মকরুহ","হারাম"],"correct_answer":1,"explanation":"হাসি কেবল নামাযের গাম্ভীর্য নষ্ট করে বলে সেখানে নিষিদ্ধ।"},{"id":80,"question":"তায়াম্মুমের সময় কব্জি থেকে হাতের আঙ্গুল পর্যন্ত মাসাহ করা কী?","options":["ফরজ","ওয়াজিব বা ফরজ","সুন্নত","নফল"],"correct_answer":1,"explanation":"পুরো হাত মাসাহ করা তায়াম্মুমের অন্যতম অঙ্গ।"},{"id":81,"question":"তাহারাত বা পবিত্রতা ঈমানের কোন অংশ হিসেবে হাদিসে বর্ণিত?","options":["অর্ধেক","এক তৃতীয়াংশ","পুরো ঈমান","কিছুই না"],"correct_answer":0,"explanation":"নবীজি (সা.) বলেছেন, পবিত্রতা হলো ঈমানের অর্ধেক।"},{"id":82,"question":"অযুর ফরজ কাজগুলোর মধ্যে কোনটি আগে করা হয়?","options":["মাথা মাসাহ","মুখ ধোয়া","পা ধোয়া","হাত ধোয়া"],"correct_answer":1,"explanation":"কুরআনে বর্ণিত ধারাবাহিকতা অনুযায়ী মুখ ধোয়া প্রথম ফরজ।"},{"id":83,"question":"অযুর সময় কুলি করার জন্য কোন হাত দিয়ে পানি মুখে নেওয়া সুন্নাত?","options":["বাম হাত","ডান হাত","উভয় হাত","আঙ্গুল"],"correct_answer":1,"explanation":"সব পবিত্র কাজে ডান হাতের অগ্রাধিকার সুন্নাত।"},{"id":84,"question":"গোসলের সময় নাকের নরম হাড় পর্যন্ত পানি পৌঁছানো কী?","options":["সুন্নত","ফরজ","নফল","ঐচ্ছিক"],"correct_answer":1,"explanation":"নাকের ভেতর পরিষ্কার করা গোসলের অবিচ্ছেদ্য অংশ।"},{"id":85,"question":"তায়াম্মুম করার সময় হাতে লেগে থাকা অতিরিক্ত মাটি ঝেড়ে ফেলা কেমন?","options":["নিষিদ্ধ","মুস্তাহাব বা সুন্নাত","মকরুহ","ওয়াজিব"],"correct_answer":1,"explanation":"মাটির ধুলো মুখে অতিরিক্ত মাখা অনুচিত, তাই ঝেড়ে নেওয়া হয়।"},{"id":86,"question":"অযুর সময় মাথা মাসাহ করার সময় কয়টি আঙ্গুল ব্যবহার করা সুন্নাত?","options":["১টি","৩টি","সবগুলো (১০টি)","৫টি"],"correct_answer":1,"explanation":"তিন আঙ্গুল দিয়ে মাথার উপরিভাগ মাসাহ করার নিয়ম বর্ণিত আছে।"},{"id":87,"question":"অযু অবস্থায় কোনো নফল নামায পড়লে আলাদা সওয়াব কী?","options":["টাকা পাওয়া","তাহিয়্যাতুল অজুর ফজিলত","বিদেশে যাওয়া","রাজত্ব"],"correct_answer":1,"explanation":"অযুর পর দুই রাকাত নামায পড়া নবীজির অত্যন্ত প্রিয় ছিল।"},{"id":88,"question":"তায়াম্মুম করার পর নামায শুরু করার আগে পানি পেলে কী করতে হয়?","options":["নামাজ চালিয়ে যাওয়া","তায়াম্মুম ছেড়ে অযু করা","সদকা দেওয়া","বিদেশে যাওয়া"],"correct_answer":1,"explanation":"পানির উপস্থিতিতে তায়াম্মুমের হুকুম বাতিল হয়ে যায়।"},{"id":89,"question":"অযুর সময় কুনুই পর্যন্ত হাত ধোয়া কয়বার সুন্নাত?","options":["১ বার","৩ বার","১০ বার","৫ বার"],"correct_answer":1,"explanation":"মুখ ও হাত তিনবার করে ধোয়া নবীজির নিয়মিত আমল।"},{"id":90,"question":"গোসলের সময় যদি দাঁতের ফাঁকে খাবার আটকে থাকে তবে কী হয়?","options":["সহীহ হবে","খাবার বের করে ঐ জায়গা ভেজানো জরুরি","মকরুহ","জানিনা"],"correct_answer":1,"explanation":"পানির বাধা দূর করা পবিত্রতা অর্জনের শর্ত।"},{"id":91,"question":"তাহারাত অর্জনের জন্য পানির প্রথম বিকল্প কোনটি?","options":["আতর","পবিত্র মাটি (তায়াম্মুম)","বালু","রঙিন পানি"],"correct_answer":1,"explanation":"আল্লাহ তায়ালা মাটিকে মুমিনের জন্য পবিত্রকারী বানিয়েছেন।"},{"id":92,"question":"অযুর সময় মাথা মাসাহর পর কান মাসাহর জন্য নতুন পানি নেওয়া কী?","options":["ওয়াজিব","সুন্নত বা মুস্তাহাব (প্রয়োজন নেই)","মকরুহ","নিষিদ্ধ"],"correct_answer":1,"explanation":"মাথা মাসাহর অবশিষ্ট পানি দিয়েই কান মাসাহ করা যায়।"},{"id":93,"question":"অযু করার পর শরীরে কোনো ক্ষত থেকে রক্ত বের হয়ে না গড়ালে কী হবে?","options":["অযু ভাঙবে","অযু নষ্ট হবে না","কাফফারা লাগবে","জানিনা"],"correct_answer":1,"explanation":"রক্তের বিন্দু প্রবাহিত না হওয়া পর্যন্ত অযু অটুট থাকে।"},{"id":94,"question":"তায়াম্মুমের সময় হাতের পিঠ ও তালু মাসাহ করা কী?","options":["নফল","ফরজ","সুন্নত","মুবাহ"],"correct_answer":1,"explanation":"হাতকে মাটির ধুলো দিয়ে মুছা তায়াম্মুমের একটি রোকন।"},{"id":95,"question":"গোসলের সময় নাভিতে পানি পৌঁছানো শরীয়তের দৃষ্টিতে কেমন?","options":["ঐচ্ছিক","ফরজ বা আবশ্যক","সুন্নত","মকরুহ"],"correct_answer":1,"explanation":"শরীরের প্রতিটি গভীর অংশে পানি পৌঁছানো গোসলের শর্ত।"},{"id":96,"question":"অযুর সময় হাতের আঙ্গুলের আংটি ঢিলে করে পানি পৌঁছানো কী?","options":["নফল","ওয়াজিব বা ফরজ","সুন্নত","মকরুহ"],"correct_answer":1,"explanation":"চামড়া ভিজে যাওয়া নিশ্চিত করা অযুর শর্ত।"},{"id":97,"question":"তায়াম্মুম কি শুধু সফর বা ভ্রমণে জায়েজ?","options":["হ্যাঁ","না, বাড়িতে অসুস্থ থাকলেও জায়েজ","শুধু হজ্জে","জানিনা"],"correct_answer":1,"explanation":"অসুস্থতা বা পানির দুষ্প্রাপ্যতা যে কোনো স্থানে ওজর হতে পারে।"},{"id":98,"question":"তাহারাতের ক্ষেত্রে কোন ধরণের পানি সবচেয়ে পবিত্র?","options":["পুকুরের পানি","বৃষ্টির পানি (আসমান থেকে পড়া)","নর্দমার পানি","বিদেশের পানি"],"correct_answer":1,"explanation":"আল্লাহ আসমান থেকে পবিত্র পানি বর্ষণ করেন।"},{"id":99,"question":"অযুর সময় পা ধোয়ার বদলে কি মোজা মাসাহ সবসময় করা যায়?","options":["হ্যাঁ","না, শর্তসাপেক্ষে (চামড়ার মোজা হলে)","পাপ","জানিনা"],"correct_answer":1,"explanation":"মোজার স্থায়িত্ব ও উপাদানের ওপর মাসাহ নির্ভর করে।"},{"id":100,"question":"গোসলের ফরজগুলো আদায় না করলে নামাযের অবস্থা কী হবে?","options":["সহীহ হবে","নামায বাতিল গণ্য হবে","সওয়াব হবে","জানিনা"],"correct_answer":1,"explanation":"পবিত্রতা ছাড়া নামায আল্লাহর দরবারে অগ্রহণযোগ্য।"},{"id":101,"question":"অযুর জন্য ব্যবহৃত পানি কেমন হওয়া উচিত?","options":["রঙিন","স্বচ্ছ, গন্ধহীন ও স্বাদহীন","গরম","মিষ্টি"],"correct_answer":1,"explanation":"পানির স্বাভাবিক বৈশিষ্ট্য অক্ষত থাকা জরুরি।"},{"id":102,"question":"তায়াম্মুম করার সময় চোখের মাসাহর বিধান কী?","options":["চোখ বন্ধ রাখা","চোখের পাতা বা উপরিভাগ মাসাহ করা","চোখ ধোয়া","জানিনা"],"correct_answer":1,"explanation":"পুরো মুখমণ্ডলের অংশ হিসেবে চোখের পাতা মাসাহর অন্তর্ভুক্ত।"},{"id":103,"question":"অযুর সময় ‘বিসমিল্লাহ’ বলতে ভুলে গেলে করণীয় কী?","options":["অযু পুনরায় করা","মাঝপথে মনে পড়লে পড়া (অযু হয়ে যাবে)","সদকা দেওয়া","কাঁদা"],"correct_answer":1,"explanation":"বিসমিল্লাহ সুন্নাত, এটি ভুলে গেলে অযু বাতিল হয় না।"},{"id":104,"question":"তাহারাতের জন্য ইস্তিনজার সময় কিবলামুখী হওয়া কেমন কাজ?","options":["সুন্নত","নিষিদ্ধ বা মকরুহ তাহরীমি","ওয়াজিব","ভালো"],"correct_answer":1,"explanation":"কিবলার দিকে মুখ বা পিঠ দিয়ে শৌচকার্য করা নিষেধ।"},{"id":105,"question":"গোসলের সময় শরীরে কোনো অলঙ্কার (নাকফুল) টাইট থাকলে কী হয়?","options":["মাফ","নাড়িয়ে নিচে পানি পৌঁছানো জরুরি","কেটে ফেলা","জানিনা"],"correct_answer":1,"explanation":"গোসলে প্রতিটি ছিদ্র ও অংশ ভেজানো ফরজ।"},{"id":106,"question":"অযুর সময় মাথা মাসাহ করার সময় টুপি বা পাগড়ি কি খোলা জরুরি?","options":["না","হ্যাঁ, মাথার অংশবিশেষ স্পর্শ করা ফরজ","মকরুহ","পাপ"],"correct_answer":1,"explanation":"চুল বা মাথার চামড়া স্পর্শ না করলে মাসাহ হবে না।"},{"id":107,"question":"তায়াম্মুম করার সময় হাতের কুনুই ধোয়া কি ফরজ?","options":["না","না, কুনুই পর্যন্ত মাসাহ করা ফরজ","হ্যাঁ","জানিনা"],"correct_answer":1,"explanation":"তায়াম্মুমে ধোয়ার বিধান নেই, কেবল মাসাহ আছে।"},{"id":108,"question":"তাহারাত অর্জনের পর আযান দিলে কি পুনরায় অযু করতে হয়?","options":["হ্যাঁ","না, অযু না ভাঙা পর্যন্ত তা বহাল থাকে","উত্তম","মাঝে মাঝে"],"correct_answer":1,"explanation":"অযু একবার করলে তা দিয়ে একাধিক নামায পড়া যায়।"},{"id":109,"question":"অযুর সময় ঘাড় মাসাহ কি মাথার মাসাহর পর করতে হয়?","options":["না","হ্যাঁ, ধারাবাহিকতা বজায় রাখা সুন্নাত","মাঝখানে","জানিনা"],"correct_answer":1,"explanation":"এটি মাথার মাসাহর শেষ অংশের সাথে সম্পর্কিত।"},{"id":110,"question":"গোসলের সময় কানে পানি ঢুকলে যদি ক্ষতি হয় তবে নিয়ম কী?","options":["পানি ঢোকানো ফরজ","কানের ভেতরে পানি না দিয়ে মাসাহ করা (ক্ষতি এড়াতে)","গোসল না করা","জানিনা"],"correct_answer":1,"explanation":"ইসলাম মানুষের জীবন ও স্বাস্থ্যের নিরাপত্তাকে প্রাধান্য দেয়।"},{"id":111,"question":"তায়াম্মুম করার পর ইবাদত শেষ হলে তায়াম্মুমের অবস্থা কী হয়?","options":["বাতিল হয়","সহীহ থাকে (যতক্ষণ ওজর থাকে বা অযু না ভাঙে)","সওয়াব কমে","হারাম হয়"],"correct_answer":1,"explanation":"তায়াম্মুম অযুর মতোই একটি অস্থায়ী পবিত্রতা মাধ্যম।"},{"id":112,"question":"অযুর সময় পায়ের আঙ্গুল খিলাল করার সঠিক পদ্ধতি কোনটি?","options":["বাম হাতের কনিষ্ঠ আঙ্গুল দিয়ে","ডান হাত দিয়ে","পা দিয়ে","ব্রাশ দিয়ে"],"correct_answer":0,"explanation":"বাম হাতের কনিষ্ঠ আঙ্গুল দিয়ে পায়ের আঙ্গুল খিলাল করা সুন্নাত।"},{"id":113,"question":"তাহারাতের ক্ষেত্রে কোন মাটি তায়াম্মুমের জন্য শ্রেষ্ঠ?","options":["বালু মাটি","শুষ্ক ও পবিত্র মাটি","কাদা","পাথরহীন"],"correct_answer":1,"explanation":"প্রাকৃতিক ও পবিত্র মাটিই সর্বোত্তম।"},{"id":114,"question":"অযুর সময় কিরাত বা জিকির পড়া কি জায়েজ?","options":["হ্যাঁ","না, অযু চলাকালীন নীরব থাকা বা দোয়া পড়া সুন্নাত","মকরুহ","হারাম"],"correct_answer":1,"explanation":"অযুর সময় দুনিয়াবী কথা না বলা উত্তম।"},{"id":115,"question":"গোসলের পর কি শরীর মোছা নবীজির সুন্নাত?","options":["না","হ্যাঁ, চাদর বা গামছা দিয়ে মোছা জায়েজ","হারাম","মকরুহ"],"correct_answer":1,"explanation":"পরিচ্ছন্নতা ও সুস্থতার জন্য মোছা যেতে পারে।"},{"id":116,"question":"তায়াম্মুমের জন্য কি আলাদা করে ওজু ও গোসলের নিয়ত করতে হয়?","options":["হ্যাঁ","না, পবিত্রতা অর্জনের একটি নিয়তই যথেষ্ট","জরুরি না","বিদেশে হয়"],"correct_answer":1,"explanation":"তায়াম্মুম একটি সমন্বিত বিকল্প পদ্ধতি।"},{"id":117,"question":"অযুর সময় চোখে চশমা থাকলে করণীয় কী?","options":["রেখে দেওয়া","চশমা খুলে মুখ ধোয়া","মুছে ফেলা","জানিনা"],"correct_answer":1,"explanation":"মুখ ধোয়ার ফরজে চশমা একটি বাধা।"},{"id":118,"question":"তাহারাতের ক্ষেত্রে সাবানের ভূমিকা কী?","options":["ফরজ","পরিচ্ছন্নতা ও সৌন্দর্য বৃদ্ধি (সুন্নাত সদৃশ)","হারাম","নিষিদ্ধ"],"correct_answer":1,"explanation":"নাপাকি দূর করতে সাবান একটি আধুনিক সহায়ক মাধ্যম।"},{"id":119,"question":"অযুর সময় কি শুধু কুলি করলেই হয় নাকি দাঁতও মাজা উচিত?","options":["কুলি যথেষ্ট","দাঁত মাজা বা মেসওয়াক করা সুন্নাত","জরুরি না","মকরুহ"],"correct_answer":1,"explanation":"দাঁত পরিষ্কার রাখা রোজার মাসেও সুন্নাত।"},{"id":120,"question":"গোসলের পর পুনরায় অযু করলে সওয়াব পাওয়া যায় কি?","options":["না","হ্যাঁ, এটি ‘অযুর ওপর অযু’ হিসেবে সওয়াবের কাজ","মকরুহ","পাপ"],"correct_answer":1,"explanation":"পবিত্রতার ওপর পবিত্রতা অর্জন নূর সমতুল্য।"},{"id":121,"question":"তায়াম্মুমের সময় কব্জি থেকে উপরের অংশ মাসাহ করা কী?","options":["নফল","সুন্নত বা ফরজ (কনুই পর্যন্ত)","মকরুহ","ঐচ্ছিক"],"correct_answer":1,"explanation":"হাত পূর্ণভাবে মাসাহ করা শর্ত।"},{"id":122,"question":"অযুর সময় নাকে পানি দেওয়ার পর নাক ঝাড়া কী?","options":["হারাম","সুন্নত ও পরিচ্ছন্নতা","ওয়াজিব","ঐচ্ছিক"],"correct_answer":1,"explanation":"নাকের ময়লা দূর করা সুন্নাত আমল।"},{"id":123,"question":"তাহারাতের জন্য ব্যবহৃত পানি কি পুনরায় ব্যবহার করা যায়?","options":["না","না, ব্যবহৃত পানি দিয়ে অযু-গোসল হয় না","হ্যাঁ","বিদেশে হয়"],"correct_answer":1,"explanation":"এই পানিকে ‘মায়ে মুস্তামাল’ বলা হয় যা পবিত্রতা অর্জনে অযোগ্য।"},{"id":124,"question":"অযুর সময় চুলে কলপ বা ডাই থাকলে অযুর হুকুম কী?","options":["অযু হবে না","যদি পানি প্রবেশে বাধা না দেয় তবে অযু হবে","হারাম","পাপ"],"correct_answer":1,"explanation":"পানির প্রতিবন্ধক না হলে পবিত্রতা সহীহ।"},{"id":125,"question":"গোসলের সময় কি লজ্জা স্থান ঢাকা রাখা সুন্নাত?","options":["না","হ্যাঁ, একাকী থাকলেও সতর ঢাকা শিষ্টাচার","জরুরি না","হারাম"],"correct_answer":1,"explanation":"আল্লাহর সামনে বিনয় ও পর্দা রক্ষা করা উত্তম।"},{"id":126,"question":"তায়াম্মুমের পর কি পুনরায় মাটি দিয়ে হাত মুছতে হয়?","options":["না","না, একবার করাই যথেষ্ট","হ্যাঁ","জানিনা"],"correct_answer":1,"explanation":"একবার সঠিক মাসাহেই পবিত্রতা অর্জিত হয়।"},{"id":127,"question":"অযুর সময় হাতের নখপালিশ থাকলে অযুর কী হবে?","options":["সহীহ","অযু হবে না (যদি তা চামড়ায় পানি পৌঁছাতে বাধা দেয়)","মকরুহ","সওয়াব"],"correct_answer":1,"explanation":"নখপালিশ পানি প্রবেশ করতে দেয় না বলে তা তুলে ফেলা জরুরি।"},{"id":128,"question":"তাহারাতের ক্ষেত্রে কোন ধরণের নাপাকিকে 'নাজাসাতে খাফিফা' বা হালকা বলা হয়?","options":["রক্ত","হালাল প্রাণীর পেশাব","মদ","বিষ্ঠা"],"correct_answer":1,"explanation":"শরিয়তে এর বিধান নাজাসাতে গালিজাহ থেকে কিছুটা শিথিল।"},{"id":129,"question":"অযুর সময় কি দুই হাত ঘষা সুন্নাত?","options":["না","হ্যাঁ, অঙ্গগুলো ঘষে ধোয়া সুন্নাত","মকরুহ","ওয়াজিব"],"correct_answer":1,"explanation":"ভালোভাবে ময়লা পরিষ্কারে এটি সহায়ক।"},{"id":130,"question":"গোসলের পর চুলে তেল মাখা কি জায়েজ?","options":["না","হ্যাঁ, এটি একটি স্বাভাবিক কাজ","হারাম","মকরুহ"],"correct_answer":1,"explanation":"পবিত্রতার পর সাজসজ্জায় বাধা নেই।"},{"id":131,"question":"তায়াম্মুমের সময় মাটির ধুলো কি সারা মুখে মাখতে হয়?","options":["হ্যাঁ","না, ধুলো ঝেড়ে ফেলে কেবল মাসাহ করতে হয়","পাথর দিয়ে","জানিনা"],"correct_answer":1,"explanation":"মুখের ওপর মাটি লেপন করা ইসলামে নেই।"},{"id":132,"question":"অযুর সময় কি কোনো বিশেষ প্যান্ট বা লুঙ্গি পরা শর্ত?","options":["হ্যাঁ","না, যেকোনো পবিত্র পোশাকেই অযু করা যায়","সাদা হতে হবে","জানিনা"],"correct_answer":1,"explanation":"পবিত্রতা ই আসল বিষয়।"},{"id":133,"question":"তাহারাত অর্জনের জন্য পানির পাত্র কি মাটির হওয়া উত্তম?","options":["হ্যাঁ","না, যেকোনো পবিত্র পাত্র (প্লাস্টিক বা ধাতু) জায়েজ","সোনার হতে হবে","জানিনা"],"correct_answer":1,"explanation":"পাত্রের উপাদানে পবিত্রতা নষ্ট হয় না।"},{"id":134,"question":"অযুর সময় যদি কোনো অঙ্গে ক্ষত থাকে তবে পানি ব্যবহারে নিষেধাজ্ঞা থাকলে কী হবে?","options":["জোর করে ধোয়া","ঐ জায়গা মাসাহ করা বা অযু ছেড়ে তায়াম্মুম করা","হারাম","জানিনা"],"correct_answer":1,"explanation":"অসুস্থতা ইসলামের একটি শক্তিশালী ওজর।"},{"id":135,"question":"গোসলের সময় কি কথা বলা মকরুহ?","options":["না","হ্যাঁ, কারণ এটি ইবাদত ও নগ্ন অবস্থার সময়","সওয়াব","জানিনা"],"correct_answer":1,"explanation":"গাম্ভীর্য ও নীরবতা বজায় রাখা শিষ্টাচার।"},{"id":136,"question":"তায়াম্মুমের পর কি পুনরায় সাহরি খাওয়া জায়েজ?","options":["না","হ্যাঁ, তায়াম্মুমের সাথে খাওয়ার কোনো বিরোধ নেই","হারাম","জানিনা"],"correct_answer":1,"explanation":"এটি কেবল সালাতের পবিত্রতার বিকল্প।"},{"id":137,"question":"অযুর সময় কি আয়নার সামনে অযু করা জায়েজ?","options":["না","হ্যাঁ, এতে শরীয়তের কোনো বাধা নেই","মকরুহ","হারাম"],"correct_answer":1,"explanation":"আয়না দেখা অযুর অংশ নয় তবে জায়েজ।"},{"id":138,"question":"তাহারাতের ক্ষেত্রে সুগন্ধি ব্যবহার করার মর্যাদা কী?","options":["ফরজ","সুন্নত ও সৌন্দর্য","হারাম","মকরুহ"],"correct_answer":1,"explanation":"নবীজি (সা.) সুগন্ধি খুব পছন্দ করতেন।"},{"id":139,"question":"অযুর পানির পাত্র কি খোলা রাখা জায়েজ?","options":["না","না, ঢেকে রাখা সুন্নাত ও স্বাস্থ্যকর","হ্যাঁ","বিদেশে জায়েজ"],"correct_answer":1,"explanation":"পানির বিশুদ্ধতা বজায় রাখা ইমানের অঙ্গ।"},{"id":140,"question":"গোসলের পর কি আতর লাগানো নবীজির শিক্ষা?","options":["না","হ্যাঁ, পরিচ্ছন্নতার পর সুঘ্রাণ ছড়ানো উত্তম","মকরুহ","জানিনা"],"correct_answer":1,"explanation":"পবিত্রতার সাথে সুঘ্রাণ মুমিনের ভূষণ।"},{"id":141,"question":"তায়াম্মুম কি দিনে কয়বার করা যায়?","options":["১ বার","যতবার অযু বা গোসলের প্রয়োজন হয়","১০ বার","জানিনা"],"correct_answer":1,"explanation":"ওজর থাকা পর্যন্ত এটি বারবার করা যায়।"},{"id":142,"question":"অযুর সময় কি কারো সাহায্য নেওয়া জায়েজ?","options":["না","হ্যাঁ, অসুস্থ বা অক্ষম হলে সাহায্য নেওয়া যায়","হারাম","মকরুহ"],"correct_answer":1,"explanation":"পরস্পর সহযোগিতা ইসলামের সৌন্দর্য।"},{"id":143,"question":"তাহারাতের জন্য কি শুধু যমযমের পানি ব্যবহার করা যাবে?","options":["না","হ্যাঁ, তবে সাধারণ পানি থাকাকালীন যমযম দিয়ে অযু-গোসল না করাই ভালো","সওয়াব","জানিনা"],"correct_answer":1,"explanation":"যমযমের পানির এক বিশেষ মর্যাদা আছে।"},{"id":144,"question":"অযুর সময় কি টুপি পরা শর্ত?","options":["হ্যাঁ","না, অযু অবস্থায় টুপি না থাকলেও অযু হবে","সুন্নত","ওয়াজিব"],"correct_answer":1,"explanation":"টুপি পরা নামাযের আদব, অযুর শর্ত নয়।"},{"id":145,"question":"গোসলের সময় যদি সাবান ফুরিয়ে যায় তবে গোসলের কী হবে?","options":["হবে না","পানি দিয়ে সারা শরীর ধুলে গোসল হবে","মকরুহ","জানিনা"],"correct_answer":1,"explanation":"সাবান অতিরিক্ত সুবিধা, মূল ফরজ হলো পানি পৌঁছানো।"},{"id":146,"question":"তায়াম্মুম কি শীতকালে বেশি ফজিলতপূর্ণ?","options":["হ্যাঁ","না, এটি কেবল প্রয়োজনে করার বিধান","মকরুহ","জানিনা"],"correct_answer":1,"explanation":"সহজতা আল্লাহর পক্ষ থেকে একটি নেয়ামত।"},{"id":147,"question":"অযুর সময় কি কিবলামুখী হওয়া জরুরি?","options":["হ্যাঁ","না, এটি মুস্তাহাব বা উত্তম কিন্তু শর্ত নয়","হারাম","জানিনা"],"correct_answer":1,"explanation":"যেকোনো দিকে ফিরেই অযু করা যায়।"},{"id":148,"question":"তাহারাতের জন্য কি সাবান ছাড়া শরীর পবিত্র হয়?","options":["না","হ্যাঁ, পানি দিয়ে ধুলে নাপাকি দূর হলে শরীর পবিত্র হয়","হারাম","জানিনা"],"correct_answer":1,"explanation":"পানিই মূল পবিত্রকারী বস্তু।"},{"id":149,"question":"অযুর সময় কি পায়ের গোড়ালি ধোয়া ফরজ?","options":["না","হ্যাঁ, এটি পা ধোয়ারই অংশ","ঐচ্ছিক","জানিনা"],"correct_answer":1,"explanation":"পা টাখনুসহ ধোয়া অযুর অন্যতম ফরজ কাজ।"},{"id":150,"question":"তাহারাত বা পবিত্রতার মূল শিক্ষা কোনটি?","options":["শরীরচর্চা","আল্লাহর আনুগত্য ও পরিচ্ছন্ন থাকা","টাকা জমানো","বিলাসিতা"],"correct_answer":1,"explanation":"পরিচ্ছন্নতা মানুষের অন্তর ও শরীরকে প্রশান্ত করে।"},{"id":151,"question":"অযুর সময় কতটুকু মাথা মাসাহ করা হানাফী মাযহাবে ফরজ?","options":["পুরো মাথা","মাথার চার ভাগের এক ভাগ","অর্ধেক মাথা","তিন আঙ্গুল পরিমাণ"],"correct_answer":1,"explanation":"ন্যূনতম এই পরিমাণ মাসাহ করলে ফরজ আদায় হয়।"},{"id":152,"question":"গোসলের সময় গড়গড়া করার ফিকহী বিধান কী?","options":["ওয়াজিব","সুন্নত (রোজা না থাকলে)","নফল","হারাম"],"correct_answer":1,"explanation":"মুখের প্রতিটি কোণ ভেজানোর জন্য গড়গড়া করা উত্তম।"},{"id":153,"question":"অযু করার পর হাত ঝাড়া দিয়ে পানি ফেলা শরীয়তে কেমন?","options":["উত্তম","মকরুহ বা অপছন্দনীয়","হারাম","সুন্নত"],"correct_answer":1,"explanation":"শান্তভাবে পানি ঝরতে দেওয়া বা মুছে ফেলা ভালো।"},{"id":154,"question":"তায়াম্মুমের সময় মাটি কি দুইবার হাত দিয়ে মারতে হয়?","options":["১ বার","২ বার (একবার মুখের জন্য, একবার হাতের জন্য)","১০ বার","৫ বার"],"correct_answer":1,"explanation":"এটি তায়াম্মুমের সুন্নাত সম্মত পদ্ধতি।"},{"id":155,"question":"তাহারাতের জন্য বৃষ্টির পানিতে গোসল করা কেমন কাজ?","options":["মকরুহ","জায়েজ ও বরকতময়","হারাম","ওয়াজিব"],"correct_answer":1,"explanation":"আসমান থেকে পড়া পানি সবচেয়ে পবিত্র ও কুদরত।"},{"id":156,"question":"অযুর সময় দুই হাতের কনুই ধোয়ার বিধান কী?","options":["সুন্নত","ফরজ","নফল","মুবাহ"],"correct_answer":1,"explanation":"কনুইসহ হাত ধোয়া অযুর একটি রোকন বা শর্ত।"},{"id":157,"question":"গোসলের সময় নখ বা চুলের গোড়ায় পানি না পৌঁছালে কী হবে?","options":["সহীহ","নাপাকি থেকে যাবে এবং গোসল হবে না","সওয়াব","জানিনা"],"correct_answer":1,"explanation":"পবিত্রতার পূর্ণতার জন্য সারা শরীর ভেজানো আবশ্যিক।"},{"id":158,"question":"তায়াম্মুম করার জন্য কি আলাদা দোয়া আছে?","options":["না","হ্যাঁ, অযুর দোয়াগুলোই এখানে প্রযোজ্য","জানি না","নতুন দোয়া"],"correct_answer":1,"explanation":"ইবাদতের মূল লক্ষ্য এক বলে দোয়ায় অমিল নেই।"},{"id":159,"question":"অযুর সময় কুলি করার আগে হাত ধোয়া কেমন কাজ?","options":["ওয়াজিব","সুন্নত","হারাম","ঐচ্ছিক"],"correct_answer":1,"explanation":"পরিচ্ছন্নতার জন্য শুরুতেই হাত ধোয়া উত্তম।"},{"id":160,"question":"তাহারাত বা ওজু করার সময় মেসওয়াক পাওয়া না গেলে কী দিয়ে করা যায়?","options":["আঙ্গুল দিয়ে ঘষে দাঁত পরিষ্কার করা","কিছু না করা","পাথর","বালি"],"correct_answer":0,"explanation":"মেসওয়াকের অভাব পূরণ করতে আঙ্গুল ব্যবহার জায়েজ।"},{"id":161,"question":"অযুর সময় কি মাথা মাসাহ করার সময় ঘাড়ও মাসাহ করতে হয়?","options":["না","হ্যাঁ, এটি একটি উত্তম ও প্রচলিত সুন্নাত","হারাম","পাপ"],"correct_answer":1,"explanation":"মাথার শেষ অংশের সাথে ঘাড়ের মাসাহ করা যায়।"},{"id":162,"question":"গোসলের পর শরীর থেকে পানি শুকিয়ে যাওয়া কি জরুরি?","options":["হ্যাঁ","না, ভেজা শরীরে কাপড় পরা জায়েজ","হারাম","মকরুহ"],"correct_answer":1,"explanation":"শুকানো ইবাদতের শর্ত নয়।"},{"id":163,"question":"তায়াম্মুম করার জন্য কি জুতো খোলা জরুরি?","options":["না","না, তবে মাটি স্পর্শ করতে কোনো বাধা না থাকা শর্ত","হ্যাঁ","মাঝে মাঝে"],"correct_answer":1,"explanation":"পবিত্রতা অর্জনের শর্তগুলো শিথিল থাকে।"},{"id":164,"question":"অযুর সময় কোন কান আগে মাসাহ করা সুন্নাত?","options":["বাম কান","ডান কান","উভয় কান একসাথে","কিছু না"],"correct_answer":2,"explanation":"কান সাধারণত মাথার মাসাহর অবিচ্ছেদ্য অংশ হিসেবে একত্রে করা হয়।"},{"id":165,"question":"তাহারাতের জন্য ব্যবহৃত মাটি কি বারবার তায়াম্মুমে ব্যবহার করা যায়?","options":["না","হ্যাঁ, যদি মাটি পবিত্র থাকে","হারাম","জানিনা"],"correct_answer":1,"explanation":"মাটি ব্যবহারের পর তার পবিত্রতা নষ্ট হয় না।"},{"id":166,"question":"অযুর সময় হাসলে কি অযু ভেঙে যায় (নামাযের বাইরে)?","options":["হ্যাঁ","না, এটি অযু ভঙ্গের কোনো কারণ নয়","মকরুহ","পাপ"],"correct_answer":1,"explanation":"হাসি কেবল নামাযের গাম্ভীর্য ভঙ্গ করে।"},{"id":167,"question":"গোসলের সময় কি সাবান মাখা সুন্নত?","options":["না","না, তবে পরিচ্ছন্নতার জন্য এটি প্রশংসনীয়","হ্যাঁ","মকরুহ"],"correct_answer":1,"explanation":"সাবান একটি আধুনিক সুবিধা।"},{"id":168,"question":"তায়াম্মুম করার পর ওজর শেষ হলে করণীয় কী?","options":["তায়াম্মুম চালিয়ে যাওয়া","দ্রুত অযু বা গোসল করে নেওয়া","কিছু না করা","জানিনা"],"correct_answer":1,"explanation":"ওজর শেষে তায়াম্মুম বাতিল হয়ে যায়।"},{"id":169,"question":"অযুর সময় কি কথা বললে অযুর সওয়াব কমে যায়?","options":["না","হ্যাঁ, অহেতুক কথায় অযুর গাম্ভীর্য নষ্ট হয়","সওয়াব বাড়ে","হারাম"],"correct_answer":1,"explanation":"নীরবতা ও জিকিরে থাকা উত্তম।"},{"id":170,"question":"তাহারাতের জন্য কি সুগন্ধি তেল মাখা জায়েজ?","options":["না","হ্যাঁ, এটি পরিচ্ছন্নতার অংশ","হারাম","মকরুহ"],"correct_answer":1,"explanation":"তেল মাখায় পবিত্রতায় কোনো সমস্যা নেই।"},{"id":171,"question":"অযুর সময় কি পা ধোয়ার সময় জুতো খোলা ফরজ?","options":["না","হ্যাঁ, পুরো পা ধোয়া ফরজ","মাঝে মাঝে","জানিনা"],"correct_answer":1,"explanation":"পা ধোয়ার জন্য চামড়া স্পর্শ করা আবশ্যিক।"},{"id":172,"question":"গোসলের সময় কি কোনো কাপড় পরা সুন্নাত?","options":["না","হ্যাঁ, একাকী থাকলেও সতর ঢাকা লজ্জাশীলতার লক্ষণ","হারাম","মকরুহ"],"correct_answer":1,"explanation":"ইসলামে মার্জিত আচরণের নির্দেশ সবখানে।"},{"id":173,"question":"তায়াম্মুম কি ছোট শিশুদের দিয়ে করানো যায়?","options":["না","হ্যাঁ, যদি তারা পানি ব্যবহারে অক্ষম হয়","হারাম","জানিনা"],"correct_answer":1,"explanation":"শিশুদেরও পবিত্র থাকার অভ্যাস করা জরুরি।"},{"id":174,"question":"অযুর সময় কি দাড়ি ভেজানো ফরজ?","options":["হ্যাঁ","না, তবে দাড়ির উপরিভাগ ধোয়া ও গোড়ায় পানি পৌঁছানো সুন্নত","হারাম","ঐচ্ছিক"],"correct_answer":1,"explanation":"দাড়ির ঘনত্ব অনুযায়ী ধোয়ার বিধান ভিন্ন।"},{"id":175,"question":"তাহারাতের জন্য কি শুধু যমযমের পানিই যথেষ্ট?","options":["না","হ্যাঁ, এটি একটি উচ্চমানের পবিত্র পানি","মকরুহ","জানিনা"],"correct_answer":1,"explanation":"যমযমের পানি বরকতময় ও পবিত্র।"},{"id":176,"question":"অযুর সময় কি কপাল ঢাকা টুপি খোলা ফরজ?","options":["না","হ্যাঁ, মুখ ধোয়ার সময় কপাল খোলা জরুরি","মকরুহ","জানিনা"],"correct_answer":1,"explanation":"মুখ ধোয়ার সীমানায় কোনো বাধা থাকা চলবে না।"},{"id":177,"question":"গোসলের সময় কি চুল কাটা জায়েজ?","options":["না","হ্যাঁ, এতে পবিত্রতায় সমস্যা নেই","হারাম","মকরুহ"],"correct_answer":1,"explanation":"গোসলের ভেতর চুল কাটার কোনো নিষেধাজ্ঞা নেই।"},{"id":178,"question":"তায়াম্মুম কি অসুস্থ ব্যক্তি নিজে করতে পারেন?","options":["না","হ্যাঁ, নিজের কাজ নিজে করা প্রশংসনীয়","হারাম","জানিনা"],"correct_answer":1,"explanation":"সামর্থ্য অনুযায়ী ইবাদত করা উচিত।"},{"id":179,"question":"অযুর সময় কি পায়ের আঙ্গুল খিলাল করা ফরজ?","options":["না","না, এটি সুন্নাত কিন্তু গুরুত্বপূর্ণ","হ্যাঁ","জানিনা"],"correct_answer":1,"explanation":"সব জায়গায় পানি পৌঁছানো নিশ্চিত করতে এটি সহায়ক।"},{"id":180,"question":"তাহারাত বা ওজু করার সময় আয়না দেখা কেমন?","options":["সওয়াব","মুবাহ বা জায়েজ","হারাম","মকরুহ"],"correct_answer":1,"explanation":"এটি পবিত্রতায় প্রভাব ফেলে না।"},{"id":181,"question":"অযুর শেষে কালিমা পড়ার পর কি জান্নাত নসীব হবে?","options":["হ্যাঁ","ইনশাআল্লাহ, নবীজি এর ফজিলত বর্ণনা করেছেন","না","জানিনা"],"correct_answer":1,"explanation":"এটি একটি বিশ্বাস ও ইবাদতের অংশ।"},{"id":182,"question":"গোসলের সময় কি গান গাওয়া জায়েজ?","options":["না","না, এটি অত্যন্ত অপছন্দনীয় কাজ","হ্যাঁ","বিদেশে জায়েজ"],"correct_answer":1,"explanation":"গোসল একটি গাম্ভীর্যপূর্ণ ইবাদত।"},{"id":183,"question":"তায়াম্মুম কি বালু মাটি ছাড়া হবে?","options":["না","হ্যাঁ, মাটির প্রকারভেদে যেকোনো পবিত্র মাটি বা পাথর হলে হবে","সওয়াব","জানিনা"],"correct_answer":1,"explanation":"মাটি জাতীয় সব বস্তুই তায়াম্মুমের জন্য বৈধ।"},{"id":184,"question":"অযুর সময় কি গামছা ব্যবহার করা সুন্নাত?","options":["না","হ্যাঁ, শরীর মোছার জন্য এটি বৈধ","হারাম","মকরুহ"],"correct_answer":1,"explanation":"সুস্থতার জন্য শরীর মোছা যেতে পারে।"},{"id":185,"question":"তাহারাতের জন্য কি গরম পানি ব্যবহার করা জায়েজ?","options":["না","হ্যাঁ, বিশেষ করে শীতকালে বা অসুস্থতায় জায়েজ","হারাম","মকরুহ"],"correct_answer":1,"explanation":"ইসলাম দ্বীনের সহজতাকে পছন্দ করে।"},{"id":186,"question":"অযুর সময় কি ঘড়ি খোলা জরুরি?","options":["না","হ্যাঁ, যদি কব্জি ধোয়ার ক্ষেত্রে তা বাধা হয়","ঐচ্ছিক","জানিনা"],"correct_answer":1,"explanation":"চামড়া স্পর্শ করা ধোয়ার শর্ত।"},{"id":187,"question":"গোসলের সময় কি চুল শুকানো জরুরি?","options":["হ্যাঁ","না, তবে সুস্থতার জন্য ভালো","হারাম","মকরুহ"],"correct_answer":1,"explanation":"এটি ইবাদতের কোনো শর্ত নয়।"},{"id":188,"question":"তায়াম্মুম কি রাতে করা জায়েজ?","options":["না","হ্যাঁ, দিনের মতো রাতেও তায়াম্মুম জায়েজ","হারাম","জানিনা"],"correct_answer":1,"explanation":"সময় তায়াম্মুমের ওপর প্রভাব ফেলে না।"},{"id":189,"question":"অযুর সময় কি কোনো বিশেষ রঙের পাত্র ব্যবহার শর্ত?","options":["হ্যাঁ","না, যেকোনো পরিষ্কার পাত্রই যথেষ্ট","সাদা হতে হবে","জানিনা"],"correct_answer":1,"explanation":"পরিচ্ছন্নতা ই আসল বিষয়।"},{"id":190,"question":"তাহারাত বা পবিত্রতার গুরুত্ব হাদিসে কিসের সাথে তুলনা করা হয়েছে?","options":["টাকার সাথে","নামাযের চাবিকাঠি হিসেবে","রাজত্বের সাথে","বিদেশের সাথে"],"correct_answer":1,"explanation":"পবিত্রতা ছাড়া নামাযের দরজা খোলে না।"},{"id":191,"question":"অযুর সময় কি কান মাসাহ করার পর হাত ধোয়া জরুরি?","options":["হ্যাঁ","না, মাথা ও কান মাসাহর মাধ্যমেই অযু সম্পন্ন হয়","মকরুহ","জানিনা"],"correct_answer":1,"explanation":"ধারাবাহিকতা বজায় রাখতে হবে।"},{"id":192,"question":"গোসলের সময় কি সাবান দিয়ে শরীর ঘষা সুন্নাত?","options":["না","না, তবে পরিচ্ছন্নতার জন্য প্রশংসনীয়","হ্যাঁ","জানিনা"],"correct_answer":1,"explanation":"এটি ময়লা দূর করতে সাহায্য করে।"},{"id":193,"question":"তায়াম্মুমের সময় কি চোখ বন্ধ রাখা উচিত?","options":["হ্যাঁ","না, স্বাভাবিক রাখা উচিত","জানিনা","বিদেশে হয়"],"correct_answer":1,"explanation":"স্বাভাবিক ভাবে মাসাহ করতে হবে।"},{"id":194,"question":"অযুর সময় কি ঘাড়ের দু’পাশ মাসাহ করা যায়?","options":["না","হ্যাঁ, এটি মুস্তাহাব হিসেবে স্বীকৃত","হারাম","জানিনা"],"correct_answer":1,"explanation":"এটি মাথার মাসাহর একটি অংশ।"},{"id":195,"question":"তাহারাতের জন্য কি বৃষ্টির পানিতে গোসল করা সওয়াব?","options":["না","হ্যাঁ, এটি আল্লাহর রহমত ও কুদরত","মকরুহ","জানিনা"],"correct_answer":1,"explanation":"প্রাকৃতিক নিয়ামত আল্লাহর বড় দান।"},{"id":196,"question":"অযুর সময় কি পায়ের গোড়ালি ঢাকা জুতো খোলা ফরজ?","options":["না","হ্যাঁ, পুরো পা ধোয়া নিশ্চিত করতে হবে","মাঝে মাঝে","জানিনা"],"correct_answer":1,"explanation":"পবিত্রতা অর্জনের শর্তগুলো মানতে হবে।"},{"id":197,"question":"গোসলের সময় কি কোনো দোয়া পড়া সুন্নাত?","options":["না","অযুর দোয়াগুলোই পড়া যেতে পারে","হারাম","জানিনা"],"correct_answer":1,"explanation":"ইবাদতের শুরু ও শেষে দোয়া করা ভালো।"},{"id":198,"question":"তায়াম্মুম কি শুধু বালি দিয়ে হবে?","options":["না","না, মাটি বা পাথর জাতীয় যেকোনো পবিত্র বস্তু দিয়ে হবে","হ্যাঁ","জানিনা"],"correct_answer":1,"explanation":"আল্লাহর জমিন সবখানেই পবিত্র।"},{"id":199,"question":"অযুর সময় কি হাত মোছা জায়েজ?","options":["না","হ্যাঁ, এটি স্বাভাবিক এবং জায়েজ","হারাম","মকরুহ"],"correct_answer":1,"explanation":"প্রয়োজনে হাত বা মুখ মোছা যেতে পারে।"},{"id":200,"question":"তাহারাত বা পবিত্রতার মূল শিক্ষা কোনটি?","options":["অহংকার বর্জন","সুস্থ ও পরিচ্ছন্ন ইমানদার জীবন গড়া","টাকা জমানো","বিলাসিতা"],"correct_answer":1,"explanation":"পবিত্রতা মুমিনকে আরও বেশি শান্ত ও শৃঙ্খলিত করে।"}]}